{"metadata": {"dbt_schema_version": "https://schemas.getdbt.com/dbt/run-results/v4.json", "dbt_version": "1.6.0", "generated_at": "2023-10-05T04:45:00.812795Z", "invocation_id": "eae7c985-8f37-4097-a4fb-d54d50eb5a1a", "env": {}}, "results": [{"status": "success", "timing": [{"name": "compile", "started_at": "2023-10-05T04:45:00.632875Z", "completed_at": "2023-10-05T04:45:00.634290Z"}, {"name": "execute", "started_at": "2023-10-05T04:45:00.635241Z", "completed_at": "2023-10-05T04:45:00.635250Z"}], "thread_id": "Thread-1 (worker)", "execution_time": 0.004280805587768555, "adapter_response": {}, "message": null, "failures": null, "unique_id": "seed.dbtlearn.seed_full_moon_dates"}, {"status": "success", "timing": [{"name": "compile", "started_at": "2023-10-05T04:45:00.638265Z", "completed_at": "2023-10-05T04:45:00.639506Z"}, {"name": "execute", "started_at": "2023-10-05T04:45:00.640682Z", "completed_at": "2023-10-05T04:45:00.640690Z"}], "thread_id": "Thread-1 (worker)", "execution_time": 0.004381418228149414, "adapter_response": {}, "message": null, "failures": null, "unique_id": "seed.dbtlearn.seed_table"}, {"status": "success", "timing": [{"name": "compile", "started_at": "2023-10-05T04:45:00.643738Z", "completed_at": "2023-10-05T04:45:00.646489Z"}, {"name": "execute", "started_at": "2023-10-05T04:45:00.647446Z", "completed_at": "2023-10-05T04:45:00.647455Z"}], "thread_id": "Thread-1 (worker)", "execution_time": 0.005631685256958008, "adapter_response": {}, "message": null, "failures": null, "unique_id": "snapshot.dbtlearn.scd_raw_listings"}, {"status": "success", "timing": [{"name": "compile", "started_at": "2023-10-05T04:45:00.650462Z", "completed_at": "2023-10-05T04:45:00.655673Z"}, {"name": "execute", "started_at": "2023-10-05T04:45:00.656602Z", "completed_at": "2023-10-05T04:45:00.656607Z"}], "thread_id": "Thread-1 (worker)", "execution_time": 0.008063316345214844, "adapter_response": {}, "message": null, "failures": null, "unique_id": "model.dbtlearn.dim_hosts_cleansed"}, {"status": "success", "timing": [{"name": "compile", "started_at": "2023-10-05T04:45:00.690960Z", "completed_at": "2023-10-05T04:45:00.699430Z"}, {"name": "execute", "started_at": "2023-10-05T04:45:00.700498Z", "completed_at": "2023-10-05T04:45:00.700506Z"}], "thread_id": "Thread-1 (worker)", "execution_time": 0.012697219848632812, "adapter_response": {}, "message": null, "failures": null, "unique_id": "model.dbtlearn.dim_listings_cleansed"}, {"status": "success", "timing": [{"name": "compile", "started_at": "2023-10-05T04:45:00.704456Z", "completed_at": "2023-10-05T04:45:00.717369Z"}, {"name": "execute", "started_at": "2023-10-05T04:45:00.718367Z", "completed_at": "2023-10-05T04:45:00.718373Z"}], "thread_id": "Thread-1 (worker)", "execution_time": 0.016313791275024414, "adapter_response": {}, "message": null, "failures": null, "unique_id": "model.dbtlearn.fct_reviews"}, {"status": "success", "timing": [{"name": "compile", "started_at": "2023-10-05T04:45:00.721865Z", "completed_at": "2023-10-05T04:45:00.725192Z"}, {"name": "execute", "started_at": "2023-10-05T04:45:00.726240Z", "completed_at": "2023-10-05T04:45:00.726246Z"}], "thread_id": "Thread-1 (worker)", "execution_time": 0.006418943405151367, "adapter_response": {}, "message": null, "failures": null, "unique_id": "model.dbtlearn.dim_listings_w_hosts"}, {"status": "success", "timing": [{"name": "compile", "started_at": "2023-10-05T04:45:00.729739Z", "completed_at": "2023-10-05T04:45:00.743546Z"}, {"name": "execute", "started_at": "2023-10-05T04:45:00.744553Z", "completed_at": "2023-10-05T04:45:00.744560Z"}], "thread_id": "Thread-1 (worker)", "execution_time": 0.016883134841918945, "adapter_response": {}, "message": null, "failures": null, "unique_id": "test.dbtlearn.accepted_values_dim_listings_cleansed_room_type__Entire_home_apt__Private_room__Shared_room__Hotel_room.a95127e3af"}, {"status": "success", "timing": [{"name": "compile", "started_at": "2023-10-05T04:45:00.748158Z", "completed_at": "2023-10-05T04:45:00.751215Z"}, {"name": "execute", "started_at": "2023-10-05T04:45:00.752191Z", "completed_at": "2023-10-05T04:45:00.752196Z"}], "thread_id": "Thread-1 (worker)", "execution_time": 0.00603938102722168, "adapter_response": {}, "message": null, "failures": null, "unique_id": "test.dbtlearn.dim_listings_minimum_nights"}, {"status": "success", "timing": [{"name": "compile", "started_at": "2023-10-05T04:45:00.755714Z", "completed_at": "2023-10-05T04:45:00.764863Z"}, {"name": "execute", "started_at": "2023-10-05T04:45:00.765858Z", "completed_at": "2023-10-05T04:45:00.765862Z"}], "thread_id": "Thread-1 (worker)", "execution_time": 0.012182950973510742, "adapter_response": {}, "message": null, "failures": null, "unique_id": "test.dbtlearn.not_null_dim_listings_cleansed_host_id.084e4105be"}, {"status": "success", "timing": [{"name": "compile", "started_at": "2023-10-05T04:45:00.769443Z", "completed_at": "2023-10-05T04:45:00.773837Z"}, {"name": "execute", "started_at": "2023-10-05T04:45:00.774844Z", "completed_at": "2023-10-05T04:45:00.774849Z"}], "thread_id": "Thread-1 (worker)", "execution_time": 0.007441043853759766, "adapter_response": {}, "message": null, "failures": null, "unique_id": "test.dbtlearn.not_null_dim_listings_cleansed_listing_id.2da437bec9"}, {"status": "success", "timing": [{"name": "compile", "started_at": "2023-10-05T04:45:00.778498Z", "completed_at": "2023-10-05T04:45:00.787074Z"}, {"name": "execute", "started_at": "2023-10-05T04:45:00.788061Z", "completed_at": "2023-10-05T04:45:00.788066Z"}], "thread_id": "Thread-1 (worker)", "execution_time": 0.011695384979248047, "adapter_response": {}, "message": null, "failures": null, "unique_id": "test.dbtlearn.relationships_dim_listings_cleansed_host_id__host_id__ref_dim_hosts_cleansed_.b53b94b2ad"}, {"status": "success", "timing": [{"name": "compile", "started_at": "2023-10-05T04:45:00.791691Z", "completed_at": "2023-10-05T04:45:00.798379Z"}, {"name": "execute", "started_at": "2023-10-05T04:45:00.799348Z", "completed_at": "2023-10-05T04:45:00.799353Z"}], "thread_id": "Thread-1 (worker)", "execution_time": 0.00968623161315918, "adapter_response": {}, "message": null, "failures": null, "unique_id": "test.dbtlearn.unique_dim_listings_cleansed_listing_id.930e4e859e"}, {"status": "success", "timing": [{"name": "compile", "started_at": "2023-10-05T04:45:00.802924Z", "completed_at": "2023-10-05T04:45:00.806107Z"}, {"name": "execute", "started_at": "2023-10-05T04:45:00.807100Z", "completed_at": "2023-10-05T04:45:00.807105Z"}], "thread_id": "Thread-1 (worker)", "execution_time": 0.006213665008544922, "adapter_response": {}, "message": null, "failures": null, "unique_id": "model.dbtlearn.mart_fullmoon_reviews"}], "elapsed_time": 1.050058126449585, "args": {"favor_state": false, "indirect_selection": "eager", "log_path": "/__w/DBT/DBT/dbt/logs", "strict_mode": false, "log_format_file": "debug", "send_anonymous_usage_stats": true, "introspect": true, "enable_legacy_logger": false, "macro_debugging": false, "defer": false, "empty_catalog": false, "profiles_dir": "/__w/DBT/DBT/dbt/pf", "write_json": true, "vars": {}, "compile": true, "version_check": true, "invocation_command": "dbt docs generate --profiles-dir /__w/DBT/DBT/dbt/pf", "log_level": "info", "print": true, "quiet": false, "log_level_file": "debug", "warn_error_options": {"include": [], "exclude": []}, "log_format": "default", "partial_parse": true, "use_colors": true, "select": [], "populate_cache": true, "printer_width": 80, "cache_selected_only": false, "project_dir": "/__w/DBT/DBT/dbt", "use_colors_file": true, "which": "generate", "static_parser": true, "exclude": [], "log_file_max_bytes": 10485760}}